Workbook

Sheet 01_Резюме
A1: PracticeFlow — инвестиционная бизнес‑модель
A2: Lean‑план на 5 000 000 ₸ для закрытия MVP‑гепов, запуска 2 пилотов и выхода на первые годовые лицензии. Базовый сценарий; не является инвестиционной рекомендацией.
J3: Период | K3: Выручка, ₸ | L3: Опер. поток, ₸
A4: Ключевые показатели | J4: ="Год 1" -> Год 1 | K4: ='05_Прогноз_3г'!B15 -> 3600000 | L4: ='05_Прогноз_3г'!B20 -> -1140000
A5: Инвестиции | C5: MVP‑программа | E5: Core burn / мес. | G5: Лицензий для BE | J5: ="Год 2" -> Год 2 | K5: ='05_Прогноз_3г'!C15 -> 10700000 | L5: ='05_Прогноз_3г'!C20 -> 2495000
A6: ='03_Допущения'!$B$6 -> 5000000 | C6: ='03_Допущения'!$B$7 -> 10 | E6: ='04_Инвестиции_5м'!$G$8 -> 420000 | G6: ='05_Прогноз_3г'!$C$24 -> 7 | J6: ="Год 3" -> Год 3 | K6: ='05_Прогноз_3г'!D15 -> 21750000 | L6: ='05_Прогноз_3г'!D20 -> 8887500
A9: Выручка — Год 3 | C9: Опер. поток — Год 2 | E9: Опер. поток — Год 3 | G9: Поток после 5 млн — Год 3
A10: ='05_Прогноз_3г'!$D$15 -> 21750000 | C10: ='05_Прогноз_3г'!$C$20 -> 2495000 | E10: ='05_Прогноз_3г'!$D$20 -> 8887500 | G10: ='05_Прогноз_3г'!$D$25 -> 5242500
A13: Инвестиционная логика
A14: 1 | B14: Закрыть критичные пользовательские гепы | C14: Publish, review/comments/history, export UI; стабилизировать Docker/PDF.
A15: 2 | B15: Проверить спрос платным пилотом | C15: 2 кафедры/факультета; замерить время проверки, активацию и конверсию в годовой договор.
A16: 3 | B16: Продать годовую лицензию | C16: Тариф + онбординг; контрактное доказательство повторяемой ценности.
A17: 4 | B17: Масштабировать только после кейсов | C17: Базовый план: 7 активных лицензий во 2‑й год и 15 — в 3‑й.

Sheet 02_BMC
A1: PracticeFlow — бизнес‑модель (BMC)
A2: B2B SaaS для управления студенческой практикой. Первичный фокус — платный пилот на уровне кафедры/факультета, затем годовая лицензия для организации.
A4: Сегменты клиентов | D4: Ценность | G4: Каналы
A5: ЛПР: заведующий кафедрой, деканат, отдел практики. Пользователи: преподаватель, студент, методист/директор. | D5: Единый путь: шаблон → отчёт → проверка → правки → итоговый документ. Меньше версий файлов, прозрачные статусы и история. | G5: Прямой пилот с кафедрой. Демонстрация на реальных экранах. Партнёрство с вузом и рекомендация между подразделениями.
A11: Отношения с клиентом | D11: Потоки выручки | G11: Ключевые действия
A12: Онбординг шаблонов и групп. Поддержка в период практики. Ежемесячный созвон по обратной связи и метрикам. | D12: Платный пилот: 350 тыс. ₸. Годовая лицензия: от 1,2 млн ₸. Разовая настройка/онбординг: 250 тыс. ₸. | G12: Закрыть UI review/publish/export. Стабилизировать Docker/PDF. Запустить 2–3 пилота и конвертировать их в годовые лицензии.
A18: Ключевые ресурсы | D18: Ключевые партнёры | G18: Структура затрат
A19: MVP-код, документный движок, команда продукта, UX-исследование, шаблоны и экспертность преподавателей. | D19: Кафедры и отделы практики, пилотные вузы, методисты, облачная инфраструктура, юридическая/закупочная поддержка. | G19: Разработка и QA, UX, облако/DevOps, онбординг, продажи и договоры. Подробное распределение — на листе 04.

Sheet 03_Допущения
A1: Допущения и драйверы
A2: Жёлтые/синие ячейки — редактируемые допущения. Все расчёты в остальных листах ссылаются на этот лист.
A4: Коммерческие и финансовые драйверы | F4: Легенда модели
A5: Показатель | B5: Значение | C5: Ед. | D5: Комментарий | F5: Синий текст | G5: Редактируемый ввод | H5: Поменяйте после интервью и котировок.
A6: Инвестиции | B6: 5000000 | C6: ₸ | D6: Рабочее допущение пользователя: 5 млн ₸. | F6: Зелёный текст | G6: Ссылка на другой лист | H6: Формула‑связь между блоками.
A7: Срок MVP‑программы | B7: 10 | C7: мес. | D7: Период для закрытия критичных UI-гепов и запуска первых пилотов. | F7: Чёрный текст | G7: Расчёт | H7: Формула внутри листа.
A8: Резерв | B8: 800000 | C8: ₸ | D8: Резерв на сдвиг сроков, интеграции и непредвиденные расходы. | F8: Сценарий | G8: Базовый | H8: Все суммы без налогов и без оценки доли инвестора.
A9: Цена платного пилота | B9: 350000 | C9: ₸ | D9: Один факультет/кафедра, один цикл практики.
A10: Годовая лицензия | B10: 1200000 | C10: ₸/год | D10: Стартовый тариф для организации до 500 активных участников.
A11: Онбординг и настройка | B11: 250000 | C11: ₸ | D11: Разовый платёж: шаблоны, группы, обучение координатора.
A12: COGS | B12: 0.15 | C12: % выручки | D12: Облако, поддержка и сопровождение клиента; предположение.
A13: Активные лицензии — Год 1 | B13: 2 | C13: шт. | D13: Две первые организации после пилота.
A14: Активные лицензии — Год 2 | B14: 7 | C14: шт. | D14: Пять новых + удержание первых двух.
A15: Активные лицензии — Год 3 | B15: 15 | C15: шт. | D15: Восемь новых + удержание действующих клиентов.
A16: Новые лицензии — Год 1 | B16: 2 | C16: шт. | D16: Конверсия первых пилотов в договор на год.
A17: Платные пилоты — Год 1 | B17: 2 | C17: шт. | D17: Пилоты должны проходить в реальном учебном цикле.
A18: Новые лицензии — Год 2 | B18: 5 | C18: шт. | D18: План продаж при наличии первых кейсов.
A19: Платные пилоты — Год 2 | B19: 3 | C19: шт. | D19: Верх воронки на следующий год.
A20: Новые лицензии — Год 3 | B20: 8 | C20: шт. | D20: Рост через рекомендации и прямые продажи.
... A25: НДС/налог на прибыль | B25: 0 | C25: % | D25: Не моделируется: зависит от юридической формы и режима налогообложения.
A27: Распределение инвестиций — вводимые статьи
A28: Статья | B28: Бюджет, ₸ | C28: Доля | D28: Привязка к MVP
A29: Продукт и frontend | B29: 1800000 | C29: =B29/$B$36 -> 0.36 | D29: Publish/review/export UI и роли Director/Admin
A30: Backend, QA и качество документов | B30: 700000 | C30: =B30/$B$36 -> 0.14 | D30: E2E-тесты, workflow, DOCX/PDF
A31: UX, дизайн и тестирование | B31: 350000 | C31: =B31/$B$36 -> 0.07 | D31: Путь преподавателя и студента; usability
A32: DevOps, облако и безопасность | B32: 300000 | C32: =B32/$B$36 -> 0.06 | D32: Docker, PDF-зависимости, логи, бэкапы
A33: Пилот и customer success | B33: 650000 | C33: =B33/$B$36 -> 0.13 | D33: Онбординг кафедр, поддержка, обучение
A34: Продажи, договоры и юридическое | B34: 400000 | C34: =B34/$B$36 -> 0.08 | D34: Коммерческое предложение, договоры, закупка
A35: Резерв | B35: 800000 | C35: =B35/$B$36 -> 0.16 | D35: Непредвиденные работы и задержки
A36: Итого | B36: =SUM(B29:B35) -> 5000000 | C36: =SUM(C29:C35) -> 1 | D36: Должно совпадать с суммой инвестиций

Sheet 04_Инвестиции_5м
A1: Распределение инвестиций — 5 млн ₸
A2: Бюджет закрывает критичные продуктовые гепы, запускает пилот и оставляет резерв. Это плановый бюджет, а не подтверждённая смета подрядчиков.
A4: Use of funds | F4: Runway и контроль исполнения
A5: Направление | B5: Что будет профинансировано | C5: Бюджет, ₸ | D5: Доля | F5: Метрика | G5: Значение | H5: Смысл
A6: Продукт и frontend | B6: UI публикации практики, review/comments/history, export/download, незакрытые роли | C6: ='03_Допущения'!$B$29 -> 1800000 | D6: =C6/$C$13 -> 0.36 | F6: Срок MVP‑программы | G6: ='03_Допущения'!$B$7 -> 10 | H6: Время на закрытие MVP и первый пилот
A7: Backend, QA и документы | B7: E2E‑проверки, стабилизация workflow и качество DOCX/PDF | C7: ='03_Допущения'!$B$30 -> 700000 | D7: =C7/$C$13 -> 0.14 | F7: Основной бюджет без резерва | G7: =SUM(C6:C11) -> 4200000 | H7: Не включает резерв
A8: UX и тестирование | B8: Сценарии преподавателя/студента, прототипирование, usability‑сессии | C8: ='03_Допущения'!$B$31 -> 350000 | D8: =C8/$C$13 -> 0.07 | F8: Средний core burn / мес. | G8: =G7/G6 -> 420000 | H8: Ориентир для контроля затрат
A9: DevOps и облако | B9: Docker, PDF‑зависимости, мониторинг, бэкапы и безопасность | C9: ='03_Допущения'!$B$32 -> 300000 | D9: =C9/$C$13 -> 0.06 | F9: Резерв в месяцах core burn | G9: =C12/G8 -> 1.9047619 | H9: Дополнительный запас при том же burn
A10: Пилот и сопровождение | B10: Онбординг кафедр, миграция шаблонов, обучение и первая линия поддержки | C10: ='03_Допущения'!$B$33 -> 650000 | D10: =C10/$C$13 -> 0.13 | F10: Плановый cash runway | G10: =C13/G8 -> 11.904762 | H10: Если резерв используется только при необходимости
A11: Продажи и договоры | B11: Пилотное коммерческое предложение, договоры, юр. и закупочная подготовка | C11: ='03_Допущения'!$B$34 -> 400000 | D11: =C11/$C$13 -> 0.08
A12: Резерв | B12: Изменение требований, интеграции, сдвиг сроков или дополнительный пилот | C12: ='03_Допущения'!$B$35 -> 800000 | D12: =C12/$C$13 -> 0.16
A13: Итого | C13: =SUM(C6:C12) -> 5000000 | D13: =SUM(D6:D12) -> 1
A16: Результат, который должен быть получен за инвестиции
A17: За 10 месяцев PracticeFlow должен превратить текущий API‑фундамент в замкнутый пользовательский маршрут: преподаватель публикует практику, студент сдаёт отчёт, преподаватель проверяет и выгружает результат. Коммерческая цель — 2 платных пилота и 2 годовые лицензии, которые формируют доказательство спроса для следующего раунда продаж.

Sheet 05_Прогноз_3г
A1: Прогноз выручки и операционного потока — 3 года
A2: Базовый сценарий, без налогов и без оценки доли инвестора. Все драйверы — с листа 03; суммы в ₸.
A4: Финансовая модель | F4: Как читать модель
A5: Показатель | B5: Год 1 | C5: Год 2 | D5: Год 3 | F5: Выручка | G5: Лицензии + пилоты + онбординг | H5: Контрактная модель B2B SaaS
A6: Активные годовые лицензии, шт. | B6: ='03_Допущения'!$B$13 -> 2 | C6: ='03_Допущения'!$B$14 -> 7 | D6: ='03_Допущения'!$B$15 -> 15 | F6: COGS | G6: Инфраструктура и сопровождение | H6: Не включает продуктовую команду
A7: Новые годовые лицензии, шт. | B7: ='03_Допущения'!$B$16 -> 2 | C7: ='03_Допущения'!$B$18 -> 5 | D7: ='03_Допущения'!$B$20 -> 8 | F7: Опер. поток | G7: Валовая прибыль − OpEx | H7: До налогообложения
A8: Платные пилоты, шт. | B8: ='03_Допущения'!$B$17 -> 2 | C8: ='03_Допущения'!$B$19 -> 3 | D8: ='03_Допущения'!$B$21 -> 5 | F8: Безубыточность | G8: Выручка, покрывающая OpEx | H8: Считается без разовых платежей
A9: Цена годовой лицензии, ₸ | B9: ='03_Допущения'!$B$10 -> 1200000 | C9: ='03_Допущения'!$B$10 -> 1200000 | D9: ='03_Допущения'!$B$10 -> 1200000 | F9: Окупаемость 5 млн | G9: Год 3 в базовом сценарии | H9: По строке накопленного потока после инвестиций
A10: Цена пилота, ₸ | B10: ='03_Допущения'!$B$9 -> 350000 | C10: ='03_Допущения'!$B$9 -> 350000 | D10: ='03_Допущения'!$B$9 -> 350000 | F10: Риск | G10: Длинный цикл закупки | H10: Сначала продаём пилот, затем годовую лицензию
A11: Онбординг, ₸ | B11: ='03_Допущения'!$B$11 -> 250000 | C11: ='03_Допущения'!$B$11 -> 250000 | D11: ='03_Допущения'!$B$11 -> 250000
A12: Выручка: годовые лицензии | B12: =B6*B9 -> 2400000 | C12: =C6*C9 -> 8400000 | D12: =D6*D9 -> 18000000
A13: Выручка: пилоты | B13: =B8*B10 -> 700000 | C13: =C8*C10 -> 1050000 | D13: =D8*D10 -> 1750000
A14: Выручка: онбординг | B14: =B7*B11 -> 500000 | C14: =C7*C11 -> 1250000 | D14: =D7*D11 -> 2000000
A15: Итого выручка | B15: =SUM(B12:B14) -> 3600000 | C15: =SUM(C12:C14) -> 10700000 | D15: =SUM(D12:D14) -> 21750000
A16: COGS, % | B16: ='03_Допущения'!$B$12 -> 0.15 | C16: ='03_Допущения'!$B$12 -> 0.15 | D16: ='03_Допущения'!$B$12 -> 0.15
A17: COGS, ₸ | B17: =B15*B16 -> 540000 | C17: =C15*C16 -> 1605000 | D17: =D15*D16 -> 3262500
A18: Валовая прибыль | B18: =B15-B17 -> 3060000 | C18: =C15-C17 -> 9095000 | D18: =D15-D17 -> 18487500
A19: Операционные расходы | B19: ='03_Допущения'!$B$22 -> 4200000 | C19: ='03_Допущения'!$B$23 -> 6600000 | D19: ='03_Допущения'!$B$24 -> 9600000
A20: Операционный денежный поток | B20: =B18-B19 -> -1140000 | C20: =C18-C19 -> 2495000 | D20: =D18-D19 -> 8887500
A21: Операционная маржа | B21: =IF(B15=0,0,B20/B15) -> -0.31666667 | C21: =IF(C15=0,0,C20/C15) -> 0.23317757 | D21: =IF(D15=0,0,D20/D15) -> 0.40862069
A22: Накопленный операционный поток | B22: =B20 -> -1140000 | C22: =B22+C20 -> 1355000 | D22: =C22+D20 -> 10242500
A23: Выручка для безубыточности | B23: =B19/(1-B16) -> 4941176.5 | C23: =C19/(1-C16) -> 7764705.9 | D23: =D19/(1-D16) -> 11294118
A24: Лицензий для безубыточности, шт. | B24: =ROUNDUP(B23/B9,0) -> 5 | C24: =ROUNDUP(C23/C9,0) -> 7 | D24: =ROUNDUP(D23/D9,0) -> 10
A25: Накопленный поток после инвестиций | B25: =B22-'03_Допущения'!$B$6 -> -6140000 | C25: =C22-'03_Допущения'!$B$6 -> -3645000 | D25: =D22-'03_Допущения'!$B$6 -> 5242500

Sheet 06_Сценарии
A1: Сценарии — чувствительность к цене и продажам
A2: Сценарии меняют ключевые драйверы Года 3. Базовая строка согласована с прогнозом на листе 05.
A4: Сценарная таблица — Год 3
A5: Сценарий | B5: Лицензия, ₸ | C5: Онбординг, ₸ | D5: Пилот, ₸ | E5: Активные лицензии | F5: Новые лицензии | G5: Пилоты | H5: COGS | I5: OpEx, ₸ | J5: Выручка, ₸ | K5: Опер. поток, ₸ | L5: Лицензий для BE
A6: Консервативный | B6: 1000000 | C6: 200000 | D6: 300000 | E6: 9 | F6: 5 | G6: 3 | H6: 0.18 | I6: 9200000 | J6: =E6*B6+F6*C6+G6*D6 -> 10900000 | K6: =J6*(1-H6)-I6 -> -262000 | L6: =ROUNDUP((I6/(1-H6))/B6,0) -> 12
A7: Базовый | B7: 1200000 | C7: 250000 | D7: 350000 | E7: 15 | F7: 8 | G7: 5 | H7: 0.15 | I7: 9600000 | J7: =E7*B7+F7*C7+G7*D7 -> 21750000 | K7: =J7*(1-H7)-I7 -> 8887500 | L7: =ROUNDUP((I7/(1-H7))/B7,0) -> 10
A8: Ускоренный | B8: 1400000 | C8: 300000 | D8: 450000 | E8: 22 | F8: 10 | G8: 7 | H8: 0.13 | I8: 11000000 | J8: =E8*B8+F8*C8+G8*D8 -> 36950000 | K8: =J8*(1-H8)-I8 -> 21146500 | L8: =ROUNDUP((I8/(1-H8))/B8,0) -> 10
A11: Интерпретация
A12: Консервативный | B12: 9 лицензий к Году 3 | C12: Выручки не хватает для роста команды | D12: Нужен грант/софинансирование или выше тариф
A13: Базовый | B13: 15 лицензий к Году 3 | C13: Окупаемость 5 млн в Году 3 | D13: Цель первого коммерческого цикла
A14: Ускоренный | B14: 22 лицензии к Году 3 | C14: Можно расширять customer success и продажи | D14: Нужен сильный канал и кейсы
A15: Правило | B15: Не снижать цену без доказанной конверсии | C15: Пилот продаёт доверие; лицензия — повторяемую ценность | D15: Сначала измерить экономию времени преподавателя
A16: Ключевая метрика | B16: Конверсия пилот → годовой договор | C16: Владелец: product/sales | D16: Цель: ≥60% после первых пилотов

Sheet 07_Проверки
A1: Проверки модели
A2: Контроль связей между бюджетом, прогнозом и базовым сценарием. Статус должен быть PASS перед использованием расчёта.
A4: MODEL STATUS
A5: Итоговый статус | B5: =IF(AND(E8="OK",E9="OK",E10="OK",E11="OK",E12="OK"),"PASS","FAIL") -> PASS
A7: Проверка | B7: Факт | C7: Ожидание | D7: Отклонение | E7: Статус | F7: Комментарий
A8: Инвестиции распределены полностью | B8: ='04_Инвестиции_5м'!$C$13 -> 5000000 | C8: ='03_Допущения'!$B$6 -> 5000000 | D8: =B8-C8 -> 0 | E8: =IF(D8=0,"OK","FAIL") -> OK | F8: Итого use of funds должен равняться 5 млн ₸.
A9: Резерв неотрицательный | B9: ='03_Допущения'!$B$8 -> 800000 | C9: =0 -> 0 | D9: =B9-C9 -> 800000 | E9: =IF(B9>=C9,"OK","FAIL") -> OK | F9: Резерв нужен для нестабильности раннего MVP.
A10: Базовая выручка Года 3 сходится | B10: ='05_Прогноз_3г'!$D$15 -> 21750000 | C10: ='06_Сценарии'!$J$7 -> 21750000 | D10: =B10-C10 -> 0 | E10: =IF(D10=0,"OK","FAIL") -> OK | F10: Базовая строка сценариев должна совпасть с прогнозом.
A11: Базовый операционный поток Года 3 сходится | B11: ='05_Прогноз_3г'!$D$20 -> 8887500 | C11: ='06_Сценарии'!$K$7 -> 8887500 | D11: =B11-C11 -> 0 | E11: =IF(D11=0,"OK","FAIL") -> OK | F11: Проверка модели доходов и затрат.
A12: Операционный поток Года 2 положительный | B12: ='05_Прогноз_3г'!$C$20 -> 2495000 | C12: =0 -> 0 | D12: =B12-C12 -> 2495000 | E12: =IF(B12>0,"OK","FAIL") -> OK | F12: Базовый план должен иметь положительный поток во втором году.

Sheet 08_Источники
A1: Источники и ограничения
A2: В модели нет внешних рыночных цен: коммерческие параметры помечены как допущения и должны быть заменены результатами пилота.
A4: ID | B4: Материал | C4: Тип | D4: Дата | E4: Как использован | F4: Ограничение / заметка | G4: Расположение
A5: S1 | B5: Аудит PracticeFlow | C5: Внутренний аудит кода | D5: 2026-08-20 | E5: Определение реализованного MVP и критичных гепов | F5: Не является коммерческой валидацией рынка. | G5: PracticeFlow_3rd_defense_audit_updated.pptx
A6: S2 | B6: Опрос преподавателей | C6: Пользовательские скриншоты Google Forms | D6: 2026-08-20 | E6: Проблема трудоёмкости и готовность к пилоту | F6: 6 ответов — качественный сигнал, не рыночная статистика. | G6: feedback/
A7: S3 | B7: Экраны MVP | C7: Пользовательские UI‑скриншоты | D7: 2026-08-20 | E7: Подтверждение текущего продуктового фокуса | F7: Не подтверждает готовность end‑to‑end review/export UI. | G7: скриншоты реализованных тем/
A8: A1 | B8: Цены, расходы, объёмы продаж | C8: Плановые допущения | D8: 2026-08-20 | E8: Финансовый прогноз и сценарии | F8: Не внешние котировки. Заменить после интервью и договорных предложений. | G8: Лист 03_Допущения
A9: A2 | B9: Курс/оценка инвестора | C9: Не используется | D9: 2026-08-20 | E9: Не рассчитывается | F9: В этой версии нет valuation, доли инвестора, налоговой модели и debt schedule. | G9: —
A12: Как улучшить модель после первых интервью
A13: Замените тарифы и затраты на фактические коммерческие предложения; добавьте воронку продаж по каждому вузу; подтвердите срок закупки; разделите пилот и годовой договор по cash‑timing; добавьте налоги и инвесторскую долю только после выбора юридической структуры и условий раунда.
